rxnopt/__init__.py
rxnopt/cli.py
rxnopt/initialize.py
rxnopt/optimize.py
rxnopt/rxnopt.py
rxnopt/bo_algorithm/GP_opt.py
rxnopt/bo_algorithm/acf_opt.py
rxnopt/descriptor/__init__.py
rxnopt/descriptor/desc_proc.py
rxnopt/descriptor/qm_desc.py
rxnopt/descriptor/spoc_desc.py
rxnopt/utils/__init__.py
rxnopt/utils/load_data.py
rxnopt/utils/logging.py
rxnopt/utils/util_func.py
rxnopt/utils/visualization.py
rxnopt/utils/write_excel.py
rxnopt-0.0.1.dist-info/licenses/LICENSE
rxnopt-0.0.1.dist-info/METADATA
rxnopt-0.0.1.dist-info/WHEEL
rxnopt-0.0.1.dist-info/entry_points.txt
rxnopt-0.0.1.dist-info/top_level.txt
rxnopt-0.0.1.dist-info/RECORD
