Metadata-Version: 2.4
Name: rxnopt
Version: 0.0.1
Summary: A multi-objective reaction optimization framework based on Bayesian optimization
Author-email: Zhenzhi Tan <zhenzhitan8@gmail.com>
Maintainer-email: Zhenzhi Tan <tanzhenzhi8@gmail.com>
License: MIT License
Project-URL: Bug Tracker, https://github.com/yourusername/reactionopt/issues
Project-URL: Documentation, https://reactionopt.readthedocs.io
Project-URL: Homepage, https://github.com/yourusername/reactionopt
Project-URL: Repository, https://github.com/yourusername/reactionopt
Keywords: chemistry,reaction optimization,bayesian optimization,machine learning,catalysis
Classifier: Development Status :: 3 - Alpha
Classifier: Intended Audience :: Science/Research
Classifier: License :: OSI Approved :: MIT License
Classifier: Operating System :: OS Independent
Classifier: Programming Language :: Python :: 3
Classifier: Topic :: Scientific/Engineering :: Chemistry
Classifier: Topic :: Scientific/Engineering :: Artificial Intelligence
Requires-Python: >=3.10
License-File: LICENSE
Requires-Dist: numpy>=1.20.0
Requires-Dist: pandas>=1.3.0
Requires-Dist: scikit-learn>=1.0.0
Requires-Dist: matplotlib>=3.3.0
Requires-Dist: seaborn>=0.11.0
Requires-Dist: openpyxl>=3.0.0
Requires-Dist: tqdm>=4.60.0
Requires-Dist: rich>=13.0.0
Requires-Dist: typer>=0.9.0
Requires-Dist: loguru>=0.7.0
Requires-Dist: pydantic>=2.0.0
Requires-Dist: torch>=2.8.0
Requires-Dist: botorch>=0.15.0
Requires-Dist: ax-platform>=0.2.0
Requires-Dist: rdkit>=2024.9.1
Requires-Dist: pyDOE>=0.3.8
Provides-Extra: dev
Requires-Dist: pytest>=6.0; extra == "dev"
Requires-Dist: pytest-cov>=2.0; extra == "dev"
Requires-Dist: black>=21.0; extra == "dev"
Requires-Dist: flake8>=3.8; extra == "dev"
Requires-Dist: mypy>=0.800; extra == "dev"
Requires-Dist: pre-commit>=2.10; extra == "dev"
Provides-Extra: docs
Requires-Dist: sphinx>=4.0; extra == "docs"
Requires-Dist: sphinx-rtd-theme>=1.0; extra == "docs"
Requires-Dist: myst-parser>=0.15; extra == "docs"
Provides-Extra: test
Requires-Dist: pytest>=6.0; extra == "test"
Requires-Dist: pytest-cov>=2.0; extra == "test"
Requires-Dist: pytest-mock>=3.0; extra == "test"
Dynamic: license-file
